{
  "resourceType" : "ConceptMap",
  "id" : "sud.type-3to4",
  "url" : "http://hl7.org/fhir/uv/xver/ConceptMap/sud.type-3to4",
  "name" : "SupplyDelivery.type3to4",
  "title" : "Mapping for SupplyDelivery.type from 3.0.2 to 4.0.1",
  "sourceScopeUri" : "http://hl7.org/fhir/3.0/StructureDefinition/SupplyDelivery#SupplyDelivery.type",
  "targetScopeUri" : "http://hl7.org/fhir/4.0/StructureDefinition/SupplyDelivery#SupplyDelivery.type",
  "group" : [{
    "source" : "http://hl7.org/fhir/3.0/supply-item-type",
    "target" : "http://terminology.hl7.org/CodeSystem/supply-item-type",
    "element" : [{
      "code" : "medication",
      "target" : [{
        "code" : "medication",
        "relationship" : "equivalent"
      }]
    },
    {
      "code" : "device",
      "target" : [{
        "code" : "device",
        "relationship" : "equivalent"
      }]
    }]
  }]
}