{
  "resourceType": "ConceptMap",
  "id": "R3-ActionParticipantType-R4-ActionParticipantType",
  "url": "http://hl7.org/fhir/uv/xver/3.0/ConceptMap/R3-ActionParticipantType-R4-ActionParticipantType",
  "version": "0.0.1",
  "name": "R3-ActionParticipantType-R4-ActionParticipantType",
  "title": "Concept map to convert a FHIR R3 ActionParticipantType into a FHIR R4 ActionParticipantType",
  "experimental": false,
  "date": "2025-12-30T16:37:19.6635834-06:00",
  "description": "Mapping for ActivityDefinition.participant.type from 3.0.2 to 4.0.1",
  "relatedArtifact": [
    {
      "type": "predecessor",
      "label": "ActivityDefinitionParticipantType3to4",
      "display": "Id: adf.pa.type-3to4\nSource: http://hl7.org/fhir/3.0/StructureDefinition/ActivityDefinition#ActivityDefinition.participant.type\nTarget: http://hl7.org/fhir/4.0/StructureDefinition/ActivityDefinition#ActivityDefinition.participant.type",
      "resource": "http://hl7.org/fhir/uv/xver/ConceptMap/adf.pa.type-3to4"
    },
    {
      "type": "predecessor",
      "label": "PlanDefinitionActionParticipantType3to4",
      "display": "Id: pdf.ac.pa.type-3to4\nSource: http://hl7.org/fhir/3.0/StructureDefinition/PlanDefinition#PlanDefinition.action.participant.type\nTarget: http://hl7.org/fhir/4.0/StructureDefinition/PlanDefinition#PlanDefinition.action.participant.type",
      "resource": "http://hl7.org/fhir/uv/xver/ConceptMap/pdf.ac.pa.type-3to4"
    }
  ],
  "sourceScopeCanonical": "http://hl7.org/fhir/ValueSet/action-participant-type|3.0.2",
  "targetScopeCanonical": "http://hl7.org/fhir/ValueSet/action-participant-type|4.0.1",
  "group": [
    {
      "source": "http://hl7.org/fhir/action-participant-type",
      "target": "http://hl7.org/fhir/action-participant-type",
      "element": [
        {
          "code": "related-person",
          "target": [
            {
              "code": "related-person",
              "relationship": "equivalent"
            }
          ]
        },
        {
          "code": "practitioner",
          "target": [
            {
              "code": "practitioner",
              "relationship": "equivalent"
            }
          ]
        },
        {
          "code": "patient",
          "target": [
            {
              "code": "patient",
              "relationship": "equivalent"
            }
          ]
        }
      ]
    }
  ]
}