{
  "resourceType" : "ConceptMap",
  "id" : "Claim.use-5to4",
  "url" : "http://hl7.org/fhir/cross-version/ConceptMap/Claim.use-5to4",
  "name" : "Claim.use5to4",
  "title" : "Mapping for Claim.use from 5.0.0 to 4.0.1",
  "sourceScopeUri" : "http://hl7.org/fhir/5.0/StructureDefinition/Claim#Claim.use",
  "targetScopeUri" : "http://hl7.org/fhir/4.0/StructureDefinition/Claim#Claim.use",
  "group" : [{
    "source" : "http://hl7.org/fhir/5.0/claim-use",
    "target" : "http://hl7.org/fhir/4.0/claim-use",
    "element" : [{
      "code" : "predetermination",
      "target" : [{
        "code" : "predetermination",
        "relationship" : "equivalent"
      }]
    },
    {
      "code" : "preauthorization",
      "target" : [{
        "code" : "preauthorization",
        "relationship" : "equivalent"
      }]
    },
    {
      "code" : "claim",
      "target" : [{
        "code" : "claim",
        "relationship" : "equivalent"
      }]
    }]
  }]
}