{
  "resourceType" : "ConceptMap",
  "id" : "cmp.se.mode-4to4b",
  "url" : "http://hl7.org/fhir/uv/xver/ConceptMap/cmp.se.mode-4to4b",
  "name" : "CompositionSectionMode4to4b",
  "title" : "Mapping for Composition.section.mode from 4.0.1 to 4.3.0",
  "experimental" : false,
  "description" : "Mapping for Composition.section.mode from 4.0.1 to 4.3.0",
  "sourceScopeUri" : "http://hl7.org/fhir/4.0/StructureDefinition/Composition#Composition.section.mode",
  "targetScopeUri" : "http://hl7.org/fhir/4.3/StructureDefinition/Composition#Composition.section.mode",
  "group" : [{
    "source" : "http://hl7.org/fhir/4.0/list-mode",
    "target" : "http://hl7.org/fhir/4.3/list-mode",
    "element" : [{
      "code" : "changes",
      "target" : [{
        "code" : "changes",
        "relationship" : "equivalent"
      }]
    },
    {
      "code" : "working",
      "target" : [{
        "code" : "working",
        "relationship" : "equivalent"
      }]
    },
    {
      "code" : "snapshot",
      "target" : [{
        "code" : "snapshot",
        "relationship" : "equivalent"
      }]
    }]
  }]
}