{
  "resourceType" : "ConceptMap",
  "id" : "pat.gender-5to4b",
  "url" : "http://hl7.org/fhir/uv/xver/ConceptMap/pat.gender-5to4b",
  "name" : "PatientGender5to4b",
  "title" : "Mapping for Patient.gender from 5.0.0 to 4.3.0",
  "experimental" : false,
  "description" : "Mapping for Patient.gender from 5.0.0 to 4.3.0",
  "sourceScopeUri" : "http://hl7.org/fhir/5.0/StructureDefinition/Patient#Patient.gender",
  "targetScopeUri" : "http://hl7.org/fhir/4.3/StructureDefinition/Patient#Patient.gender",
  "group" : [{
    "source" : "http://hl7.org/fhir/5.0/administrative-gender",
    "target" : "http://hl7.org/fhir/4.3/administrative-gender",
    "element" : [{
      "code" : "other",
      "target" : [{
        "code" : "other",
        "relationship" : "equivalent"
      }]
    },
    {
      "code" : "female",
      "target" : [{
        "code" : "female",
        "relationship" : "equivalent"
      }]
    },
    {
      "code" : "male",
      "target" : [{
        "code" : "male",
        "relationship" : "equivalent"
      }]
    },
    {
      "code" : "unknown",
      "target" : [{
        "code" : "unknown",
        "relationship" : "equivalent"
      }]
    }]
  }]
}