{
  "resourceType" : "ConceptMap",
  "id" : "nor.en.routeofAdministration-3to4",
  "url" : "http://hl7.org/fhir/uv/xver/ConceptMap/nor.en.routeofAdministration-3to4",
  "name" : "NutritionOrder.enteralFormula.routeofAdministration3to4",
  "title" : "Mapping for NutritionOrder.enteralFormula.routeofAdministration from 3.0.2 to 4.0.1",
  "sourceScopeUri" : "http://hl7.org/fhir/3.0/StructureDefinition/NutritionOrder#NutritionOrder.enteralFormula.routeofAdministration",
  "targetScopeUri" : "http://hl7.org/fhir/4.0/StructureDefinition/NutritionOrder#NutritionOrder.enteralFormula.routeofAdministration",
  "group" : [{
    "source" : "http://hl7.org/fhir/3.0/v3/RouteOfAdministration",
    "target" : "http://terminology.hl7.org/CodeSystem/v3-RouteOfAdministration",
    "element" : [{
      "code" : "IDISCINJ",
      "target" : [{
        "code" : "IDISCINJ",
        "relationship" : "equivalent"
      }]
    },
    {
      "code" : "_SoftTissueRoute",
      "target" : [{
        "code" : "_SoftTissueRoute",
        "relationship" : "equivalent"
      }]
    },
    {
      "code" : "BILINJ",
      "target" : [{
        "code" : "BILINJ",
        "relationship" : "equivalent"
      }]
    },
    {
      "code" : "_IntracavernosalRoute",
      "target" : [{
        "code" : "_IntracavernosalRoute",
        "relationship" : "equivalent"
      }]
    },
    {
      "code" : "SQIMPLNT",
      "target" : [{
        "code" : "SQIMPLNT",
        "relationship" : "equivalent"
      }]
    },
    {
      "code" : "ICISTERNINJ",
      "target" : [{
        "code" : "ICISTERNINJ",
        "relationship" : "equivalent"
      }]
    },
    {
      "code" : "ICORONINJP",
      "target" : [{
        "code" : "ICORONINJP",
        "relationship" : "equivalent"
      }]
    },
    {
      "code" : "CHOLINJ",
      "target" : [{
        "code" : "CHOLINJ",
        "relationship" : "equivalent"
      }]
    },
    {
      "code" : "RETENEMA",
      "target" : [{
        "code" : "RETENEMA",
        "relationship" : "equivalent"
      }]
    },
    {
      "code" : "ILYMPJINJ",
      "target" : [{
        "code" : "ILYMPJINJ",
        "relationship" : "equivalent"
      }]
    },
    {
      "code" : "LARYNGTA",
      "target" : [{
        "code" : "LARYNGTA",
        "relationship" : "equivalent"
      }]
    },
    {
      "code" : "NASINHL",
      "target" : [{
        "code" : "NASINHL",
        "relationship" : "equivalent"
      }]
    },
    {
      "code" : "SININSTIL",
      "target" : [{
        "code" : "SININSTIL",
        "relationship" : "equivalent"
      }]
    },
    {
      "code" : "_IntrathecalRoute",
      "target" : [{
        "code" : "_IntrathecalRoute",
        "relationship" : "equivalent"
      }]
    },
    {
      "code" : "_IntratesticularRoute",
      "target" : [{
        "code" : "_IntratesticularRoute",
        "relationship" : "equivalent"
      }]
    },
    {
      "code" : "IVENTINJ",
      "target" : [{
        "code" : "IVENTINJ",
        "relationship" : "equivalent"
      }]
    },
    {
      "code" : "IILEALINJ",
      "target" : [{
        "code" : "IILEALINJ",
        "relationship" : "equivalent"
      }]
    },
    {
      "code" : "IONTO",
      "target" : [{
        "code" : "IONTO",
        "relationship" : "equivalent"
      }]
    },
    {
      "code" : "_Enema",
      "target" : [{
        "code" : "_Enema",
        "relationship" : "equivalent"
      }]
    },
    {
      "code" : "_RetrobulbarRoute",
      "target" : [{
        "code" : "_RetrobulbarRoute",
        "relationship" : "equivalent"
      }]
    },
    {
      "code" : "EPIINJ",
      "target" : [{
        "code" : "EPIINJ",
        "relationship" : "equivalent"
      }]
    },
    {
      "code" : "IVRPUSH",
      "target" : [{
        "code" : "IVRPUSH",
        "relationship" : "equivalent"
      }]
    },
    {
      "code" : "_SuppositoryRoute",
      "target" : [{
        "code" : "_SuppositoryRoute",
        "relationship" : "equivalent"
      }]
    },
    {
      "code" : "_IntratrachealRoute",
      "target" : [{
        "code" : "_IntratrachealRoute",
        "relationship" : "equivalent"
      }]
    },
    {
      "code" : "_OticRoute",
      "target" : [{
        "code" : "_OticRoute",
        "relationship" : "equivalent"
      }]
    },
    {
      "code" : "IURETINJ",
      "target" : [{
        "code" : "IURETINJ",
        "relationship" : "equivalent"
      }]
    },
    {
      "code" : "_GingivalRoute",
      "target" : [{
        "code" : "_GingivalRoute",
        "relationship" : "equivalent"
      }]
    },
    {
      "code" : "_PeriodontalRoute",
      "target" : [{
        "code" : "_PeriodontalRoute",
        "relationship" : "equivalent"
      }]
    },
    {
      "code" : "ICOR",
      "target" : [{
        "code" : "ICOR",
        "relationship" : "equivalent"
      }]
    },
    {
      "code" : "ICORONTA",
      "target" : [{
        "code" : "ICORONTA",
        "relationship" : "equivalent"
      }]
    },
    {
      "code" : "URETINJ",
      "target" : [{
        "code" : "URETINJ",
        "relationship" : "equivalent"
      }]
    },
    {
      "code" : "_IntracorpusCavernosumRoute",
      "target" : [{
        "code" : "_IntracorpusCavernosumRoute",
        "relationship" : "equivalent"
      }]
    },
    {
      "code" : "SHAMPOO",
      "target" : [{
        "code" : "SHAMPOO",
        "relationship" : "equivalent"
      }]
    },
    {
      "code" : "_IntraprostaticRoute",
      "target" : [{
        "code" : "_IntraprostaticRoute",
        "relationship" : "equivalent"
      }]
    },
    {
      "code" : "ITYMPINJ",
      "target" : [{
        "code" : "ITYMPINJ",
        "relationship" : "equivalent"
      }]
    },
    {
      "code" : "_IntramedullaryRoute",
      "target" : [{
        "code" : "_IntramedullaryRoute",
        "relationship" : "equivalent"
      }]
    },
    {
      "code" : "IDUODINSTIL",
      "target" : [{
        "code" : "IDUODINSTIL",
        "relationship" : "equivalent"
      }]
    },
    {
      "code" : "GUIRR",
      "target" : [{
        "code" : "GUIRR",
        "relationship" : "equivalent"
      }]
    },
    {
      "code" : "OCDRESTA",
      "target" : [{
        "code" : "OCDRESTA",
        "relationship" : "equivalent"
      }]
    },
    {
      "code" : "_IntrabronchialRoute",
      "target" : [{
        "code" : "_IntrabronchialRoute",
        "relationship" : "equivalent"
      }]
    },
    {
      "code" : "VENT",
      "target" : [{
        "code" : "VENT",
        "relationship" : "equivalent"
      }]
    },
    {
      "code" : "_Swish",
      "target" : [{
        "code" : "_Swish",
        "relationship" : "equivalent"
      }]
    },
    {
      "code" : "ENEMA",
      "target" : [{
        "code" : "ENEMA",
        "relationship" : "equivalent"
      }]
    },
    {
      "code" : "_OromucosalRoute",
      "target" : [{
        "code" : "_OromucosalRoute",
        "relationship" : "equivalent"
      }]
    },
    {
      "code" : "PCA",
      "target" : [{
        "code" : "PCA",
        "relationship" : "equivalent"
      }]
    },
    {
      "code" : "VENTMASK",
      "target" : [{
        "code" : "VENTMASK",
        "relationship" : "equivalent"
      }]
    },
    {
      "code" : "ITESTINJ",
      "target" : [{
        "code" : "ITESTINJ",
        "relationship" : "equivalent"
      }]
    },
    {
      "code" : "PAINJ",
      "target" : [{
        "code" : "PAINJ",
        "relationship" : "equivalent"
      }]
    },
    {
      "code" : "IVPUSH",
      "target" : [{
        "code" : "IVPUSH",
        "relationship" : "equivalent"
      }]
    },
    {
      "code" : "OPTHALTA",
      "target" : [{
        "code" : "OPTHALTA",
        "relationship" : "equivalent"
      }]
    },
    {
      "code" : "IVC",
      "target" : [{
        "code" : "IVC",
        "relationship" : "equivalent"
      }]
    },
    {
      "code" : "IOVARINJ",
      "target" : [{
        "code" : "IOVARINJ",
        "relationship" : "equivalent"
      }]
    },
    {
      "code" : "_PerianalRoute",
      "target" : [{
        "code" : "_PerianalRoute",
        "relationship" : "equivalent"
      }]
    },
    {
      "code" : "_TransplacentalRoute",
      "target" : [{
        "code" : "_TransplacentalRoute",
        "relationship" : "equivalent"
      }]
    },
    {
      "code" : "_JejunumRoute",
      "target" : [{
        "code" : "_JejunumRoute",
        "relationship" : "equivalent"
      }]
    },
    {
      "code" : "NASNEB",
      "target" : [{
        "code" : "NASNEB",
        "relationship" : "equivalent"
      }]
    },
    {
      "code" : "_ElectroOsmosisRoute",
      "target" : [{
        "code" : "_ElectroOsmosisRoute",
        "relationship" : "equivalent"
      }]
    },
    {
      "code" : "_ParanasalSinusesRoute",
      "target" : [{
        "code" : "_ParanasalSinusesRoute",
        "relationship" : "equivalent"
      }]
    },
    {
      "code" : "OROPHARTA",
      "target" : [{
        "code" : "OROPHARTA",
        "relationship" : "equivalent"
      }]
    },
    {
      "code" : "_UrinaryTractRoute",
      "target" : [{
        "code" : "_UrinaryTractRoute",
        "relationship" : "equivalent"
      }]
    },
    {
      "code" : "_BuccalMucosaRoute",
      "target" : [{
        "code" : "_BuccalMucosaRoute",
        "relationship" : "equivalent"
      }]
    },
    {
      "code" : "IGASTLAV",
      "target" : [{
        "code" : "IGASTLAV",
        "relationship" : "equivalent"
      }]
    },
    {
      "code" : "_MucosalAbsorptionRoute",
      "target" : [{
        "code" : "_MucosalAbsorptionRoute",
        "relationship" : "equivalent"
      }]
    },
    {
      "code" : "TMUCTA",
      "target" : [{
        "code" : "TMUCTA",
        "relationship" : "equivalent"
      }]
    },
    {
      "code" : "TRNSDERM",
      "target" : [{
        "code" : "TRNSDERM",
        "relationship" : "equivalent"
      }]
    },
    {
      "code" : "NASOGASINSTIL",
      "target" : [{
        "code" : "NASOGASINSTIL",
        "relationship" : "equivalent"
      }]
    },
    {
      "code" : "_LingualRoute",
      "target" : [{
        "code" : "_LingualRoute",
        "relationship" : "equivalent"
      }]
    },
    {
      "code" : "_RespiratoryTractRoute",
      "target" : [{
        "code" : "_RespiratoryTractRoute",
        "relationship" : "equivalent"
      }]
    },
    {
      "code" : "ORNEB",
      "target" : [{
        "code" : "ORNEB",
        "relationship" : "equivalent"
      }]
    },
    {
      "code" : "_IontophoresisRoute",
      "target" : [{
        "code" : "_IontophoresisRoute",
        "relationship" : "equivalent"
      }]
    },
    {
      "code" : "INTERMENINJ",
      "target" : [{
        "code" : "INTERMENINJ",
        "relationship" : "equivalent"
      }]
    },
    {
      "code" : "_IntraarterialRoute",
      "target" : [{
        "code" : "_IntraarterialRoute",
        "relationship" : "equivalent"
      }]
    },
    {
      "code" : "_IntracaudalRoute",
      "target" : [{
        "code" : "_IntracaudalRoute",
        "relationship" : "equivalent"
      }]
    },
    {
      "code" : "_IntrabursalRoute",
      "target" : [{
        "code" : "_IntrabursalRoute",
        "relationship" : "equivalent"
      }]
    },
    {
      "code" : "ISTERINJ",
      "target" : [{
        "code" : "ISTERINJ",
        "relationship" : "equivalent"
      }]
    },
    {
      "code" : "_Implantation",
      "target" : [{
        "code" : "_Implantation",
        "relationship" : "equivalent"
      }]
    },
    {
      "code" : "GT",
      "target" : [{
        "code" : "GT",
        "relationship" : "equivalent"
      }]
    },
    {
      "code" : "IDINJ",
      "target" : [{
        "code" : "IDINJ",
        "relationship" : "equivalent"
      }]
    },
    {
      "code" : "TRTYMPINSTIL",
      "target" : [{
        "code" : "TRTYMPINSTIL",
        "relationship" : "equivalent"
      }]
    },
    {
      "code" : "URETHSUP",
      "target" : [{
        "code" : "URETHSUP",
        "relationship" : "equivalent"
      }]
    },
    {
      "code" : "_ParenteralRoute",
      "target" : [{
        "code" : "_ParenteralRoute",
        "relationship" : "equivalent"
      }]
    },
    {
      "code" : "_ExtracorporealCirculationRoute",
      "target" : [{
        "code" : "_ExtracorporealCirculationRoute",
        "relationship" : "equivalent"
      }]
    },
    {
      "code" : "IOINJ",
      "target" : [{
        "code" : "IOINJ",
        "relationship" : "equivalent"
      }]
    },
    {
      "code" : "_SubcutaneousRoute",
      "target" : [{
        "code" : "_SubcutaneousRoute",
        "relationship" : "equivalent"
      }]
    },
    {
      "code" : "SQSURGINS",
      "target" : [{
        "code" : "SQSURGINS",
        "relationship" : "equivalent"
      }]
    },
    {
      "code" : "_CecostomyRoute",
      "target" : [{
        "code" : "_CecostomyRoute",
        "relationship" : "equivalent"
      }]
    },
    {
      "code" : "_IntraepidermalRoute",
      "target" : [{
        "code" : "_IntraepidermalRoute",
        "relationship" : "equivalent"
      }]
    },
    {
      "code" : "EPI",
      "target" : [{
        "code" : "EPI",
        "relationship" : "equivalent"
      }]
    },
    {
      "code" : "_LaryngealRoute",
      "target" : [{
        "code" : "_LaryngealRoute",
        "relationship" : "equivalent"
      }]
    },
    {
      "code" : "GBINJ",
      "target" : [{
        "code" : "GBINJ",
        "relationship" : "equivalent"
      }]
    },
    {
      "code" : "PDPINJ",
      "target" : [{
        "code" : "PDPINJ",
        "relationship" : "equivalent"
      }]
    },
    {
      "code" : "CAPDINSTL",
      "target" : [{
        "code" : "CAPDINSTL",
        "relationship" : "equivalent"
      }]
    },
    {
      "code" : "IPINJ",
      "target" : [{
        "code" : "IPINJ",
        "relationship" : "equivalent"
      }]
    },
    {
      "code" : "JJTINSTL",
      "target" : [{
        "code" : "JJTINSTL",
        "relationship" : "equivalent"
      }]
    },
    {
      "code" : "IARTINJ",
      "target" : [{
        "code" : "IARTINJ",
        "relationship" : "equivalent"
      }]
    },
    {
      "code" : "IA",
      "target" : [{
        "code" : "IA",
        "relationship" : "equivalent"
      }]
    },
    {
      "code" : "_OralRoute",
      "target" : [{
        "code" : "_OralRoute",
        "relationship" : "equivalent"
      }]
    },
    {
      "code" : "_IntravesicleRoute",
      "target" : [{
        "code" : "_IntravesicleRoute",
        "relationship" : "equivalent"
      }]
    },
    {
      "code" : "IC",
      "target" : [{
        "code" : "IC",
        "relationship" : "equivalent"
      }]
    },
    {
      "code" : "ILTOP",
      "target" : [{
        "code" : "ILTOP",
        "relationship" : "equivalent"
      }]
    },
    {
      "code" : "_IntrauterineRoute",
      "target" : [{
        "code" : "_IntrauterineRoute",
        "relationship" : "equivalent"
      }]
    },
    {
      "code" : "REBREATH",
      "target" : [{
        "code" : "REBREATH",
        "relationship" : "equivalent"
      }]
    },
    {
      "code" : "ICAVINJ",
      "target" : [{
        "code" : "ICAVINJ",
        "relationship" : "equivalent"
      }]
    },
    {
      "code" : "IM",
      "target" : [{
        "code" : "IM",
        "relationship" : "equivalent"
      }]
    },
    {
      "code" : "VAGINS",
      "target" : [{
        "code" : "VAGINS",
        "relationship" : "equivalent"
      }]
    },
    {
      "code" : "_IntravascularRoute",
      "target" : [{
        "code" : "_IntravascularRoute",
        "relationship" : "equivalent"
      }]
    },
    {
      "code" : "_SinusUnspecifiedRoute",
      "target" : [{
        "code" : "_SinusUnspecifiedRoute",
        "relationship" : "equivalent"
      }]
    },
    {
      "code" : "HEMOPORT",
      "target" : [{
        "code" : "HEMOPORT",
        "relationship" : "equivalent"
      }]
    },
    {
      "code" : "IBRONCHINSTIL",
      "target" : [{
        "code" : "IBRONCHINSTIL",
        "relationship" : "equivalent"
      }]
    },
    {
      "code" : "IT",
      "target" : [{
        "code" : "IT",
        "relationship" : "equivalent"
      }]
    },
    {
      "code" : "IUINJC",
      "target" : [{
        "code" : "IUINJC",
        "relationship" : "equivalent"
      }]
    },
    {
      "code" : "IPERINJ",
      "target" : [{
        "code" : "IPERINJ",
        "relationship" : "equivalent"
      }]
    },
    {
      "code" : "IU",
      "target" : [{
        "code" : "IU",
        "relationship" : "equivalent"
      }]
    },
    {
      "code" : "IV",
      "target" : [{
        "code" : "IV",
        "relationship" : "equivalent"
      }]
    },
    {
      "code" : "_IntraduodenalRoute",
      "target" : [{
        "code" : "_IntraduodenalRoute",
        "relationship" : "equivalent"
      }]
    },
    {
      "code" : "_SubarachnoidRoute",
      "target" : [{
        "code" : "_SubarachnoidRoute",
        "relationship" : "equivalent"
      }]
    },
    {
      "code" : "_PeriduralRoute",
      "target" : [{
        "code" : "_PeriduralRoute",
        "relationship" : "equivalent"
      }]
    },
    {
      "code" : "IVITINJ",
      "target" : [{
        "code" : "IVITINJ",
        "relationship" : "equivalent"
      }]
    },
    {
      "code" : "NASAL",
      "target" : [{
        "code" : "NASAL",
        "relationship" : "equivalent"
      }]
    },
    {
      "code" : "CERVINS",
      "target" : [{
        "code" : "CERVINS",
        "relationship" : "equivalent"
      }]
    },
    {
      "code" : "ICARDINJ",
      "target" : [{
        "code" : "ICARDINJ",
        "relationship" : "equivalent"
      }]
    },
    {
      "code" : "IDURINJ",
      "target" : [{
        "code" : "IDURINJ",
        "relationship" : "equivalent"
      }]
    },
    {
      "code" : "_Nebulization",
      "target" : [{
        "code" : "_Nebulization",
        "relationship" : "equivalent"
      }]
    },
    {
      "code" : "IOIRR",
      "target" : [{
        "code" : "IOIRR",
        "relationship" : "equivalent"
      }]
    },
    {
      "code" : "ENDOSININJ",
      "target" : [{
        "code" : "ENDOSININJ",
        "relationship" : "equivalent"
      }]
    },
    {
      "code" : "_IntrailealRoute",
      "target" : [{
        "code" : "_IntrailealRoute",
        "relationship" : "equivalent"
      }]
    },
    {
      "code" : "IBURSINJ",
      "target" : [{
        "code" : "IBURSINJ",
        "relationship" : "equivalent"
      }]
    },
    {
      "code" : "ICARDINJSP",
      "target" : [{
        "code" : "ICARDINJSP",
        "relationship" : "equivalent"
      }]
    },
    {
      "code" : "_EndocervicalRoute",
      "target" : [{
        "code" : "_EndocervicalRoute",
        "relationship" : "equivalent"
      }]
    },
    {
      "code" : "SKIN",
      "target" : [{
        "code" : "SKIN",
        "relationship" : "equivalent"
      }]
    },
    {
      "code" : "_MucousMembraneRoute",
      "target" : [{
        "code" : "_MucousMembraneRoute",
        "relationship" : "equivalent"
      }]
    },
    {
      "code" : "_IntracornealRoute",
      "target" : [{
        "code" : "_IntracornealRoute",
        "relationship" : "equivalent"
      }]
    },
    {
      "code" : "PNSINJ",
      "target" : [{
        "code" : "PNSINJ",
        "relationship" : "equivalent"
      }]
    },
    {
      "code" : "_HairRoute",
      "target" : [{
        "code" : "_HairRoute",
        "relationship" : "equivalent"
      }]
    },
    {
      "code" : "_SublingualRoute",
      "target" : [{
        "code" : "_SublingualRoute",
        "relationship" : "equivalent"
      }]
    },
    {
      "code" : "NEB",
      "target" : [{
        "code" : "NEB",
        "relationship" : "equivalent"
      }]
    },
    {
      "code" : "_InterstitialRoute",
      "target" : [{
        "code" : "_InterstitialRoute",
        "relationship" : "equivalent"
      }]
    },
    {
      "code" : "ICARDINJRP",
      "target" : [{
        "code" : "ICARDINJRP",
        "relationship" : "equivalent"
      }]
    },
    {
      "code" : "CERVINJ",
      "target" : [{
        "code" : "CERVINJ",
        "relationship" : "equivalent"
      }]
    },
    {
      "code" : "IPPB",
      "target" : [{
        "code" : "IPPB",
        "relationship" : "equivalent"
      }]
    },
    {
      "code" : "OGT",
      "target" : [{
        "code" : "OGT",
        "relationship" : "equivalent"
      }]
    },
    {
      "code" : "_RectalRoute",
      "target" : [{
        "code" : "_RectalRoute",
        "relationship" : "equivalent"
      }]
    },
    {
      "code" : "ICARINJP",
      "target" : [{
        "code" : "ICARINJP",
        "relationship" : "equivalent"
      }]
    },
    {
      "code" : "SCALP",
      "target" : [{
        "code" : "SCALP",
        "relationship" : "equivalent"
      }]
    },
    {
      "code" : "_IntragastricRoute",
      "target" : [{
        "code" : "_IntragastricRoute",
        "relationship" : "equivalent"
      }]
    },
    {
      "code" : "IPROSTINJ",
      "target" : [{
        "code" : "IPROSTINJ",
        "relationship" : "equivalent"
      }]
    },
    {
      "code" : "_IntraductalRoute",
      "target" : [{
        "code" : "_IntraductalRoute",
        "relationship" : "equivalent"
      }]
    },
    {
      "code" : "_Chew",
      "target" : [{
        "code" : "_Chew",
        "relationship" : "equivalent"
      }]
    },
    {
      "code" : "PNINJ",
      "target" : [{
        "code" : "PNINJ",
        "relationship" : "equivalent"
      }]
    },
    {
      "code" : "ENTINSTL",
      "target" : [{
        "code" : "ENTINSTL",
        "relationship" : "equivalent"
      }]
    },
    {
      "code" : "PERINEAL",
      "target" : [{
        "code" : "PERINEAL",
        "relationship" : "equivalent"
      }]
    },
    {
      "code" : "IDIMPLNT",
      "target" : [{
        "code" : "IDIMPLNT",
        "relationship" : "equivalent"
      }]
    },
    {
      "code" : "_RouteBySite",
      "target" : [{
        "code" : "_RouteBySite",
        "relationship" : "equivalent"
      }]
    },
    {
      "code" : "ELECTOSMOS",
      "target" : [{
        "code" : "ELECTOSMOS",
        "relationship" : "equivalent"
      }]
    },
    {
      "code" : "_IntrasynovialRoute",
      "target" : [{
        "code" : "_IntrasynovialRoute",
        "relationship" : "equivalent"
      }]
    },
    {
      "code" : "_EpiduralRoute",
      "target" : [{
        "code" : "_EpiduralRoute",
        "relationship" : "equivalent"
      }]
    },
    {
      "code" : "_VitreousHumourRoute",
      "target" : [{
        "code" : "_VitreousHumourRoute",
        "relationship" : "equivalent"
      }]
    },
    {
      "code" : "ICAVITINJ",
      "target" : [{
        "code" : "ICAVITINJ",
        "relationship" : "equivalent"
      }]
    },
    {
      "code" : "SWAB",
      "target" : [{
        "code" : "SWAB",
        "relationship" : "equivalent"
      }]
    },
    {
      "code" : "_IntraduralRoute",
      "target" : [{
        "code" : "_IntraduralRoute",
        "relationship" : "equivalent"
      }]
    },
    {
      "code" : "NASINHLC",
      "target" : [{
        "code" : "NASINHLC",
        "relationship" : "equivalent"
      }]
    },
    {
      "code" : "IEPITHINJ",
      "target" : [{
        "code" : "IEPITHINJ",
        "relationship" : "equivalent"
      }]
    },
    {
      "code" : "EPINJSP",
      "target" : [{
        "code" : "EPINJSP",
        "relationship" : "equivalent"
      }]
    },
    {
      "code" : "AMNINJ",
      "target" : [{
        "code" : "AMNINJ",
        "relationship" : "equivalent"
      }]
    },
    {
      "code" : "ETNEB",
      "target" : [{
        "code" : "ETNEB",
        "relationship" : "equivalent"
      }]
    },
    {
      "code" : "_InterameningealRoute",
      "target" : [{
        "code" : "_InterameningealRoute",
        "relationship" : "equivalent"
      }]
    },
    {
      "code" : "_GastricRoute",
      "target" : [{
        "code" : "_GastricRoute",
        "relationship" : "equivalent"
      }]
    },
    {
      "code" : "IVFLUSH",
      "target" : [{
        "code" : "IVFLUSH",
        "relationship" : "equivalent"
      }]
    },
    {
      "code" : "IESOPHTA",
      "target" : [{
        "code" : "IESOPHTA",
        "relationship" : "equivalent"
      }]
    },
    {
      "code" : "NGT",
      "target" : [{
        "code" : "NGT",
        "relationship" : "equivalent"
      }]
    },
    {
      "code" : "_IntracoronaryRoute",
      "target" : [{
        "code" : "_IntracoronaryRoute",
        "relationship" : "equivalent"
      }]
    },
    {
      "code" : "_IntracervicalRoute",
      "target" : [{
        "code" : "_IntracervicalRoute",
        "relationship" : "equivalent"
      }]
    },
    {
      "code" : "ICORONINJ",
      "target" : [{
        "code" : "ICORONINJ",
        "relationship" : "equivalent"
      }]
    },
    {
      "code" : "_IntramuscularRoute",
      "target" : [{
        "code" : "_IntramuscularRoute",
        "relationship" : "equivalent"
      }]
    },
    {
      "code" : "TTYMPTABSORP",
      "target" : [{
        "code" : "TTYMPTABSORP",
        "relationship" : "equivalent"
      }]
    },
    {
      "code" : "_IntrasternalRoute",
      "target" : [{
        "code" : "_IntrasternalRoute",
        "relationship" : "equivalent"
      }]
    },
    {
      "code" : "IPLRINJ",
      "target" : [{
        "code" : "IPLRINJ",
        "relationship" : "equivalent"
      }]
    },
    {
      "code" : "_IntracerebralRoute",
      "target" : [{
        "code" : "_IntracerebralRoute",
        "relationship" : "equivalent"
      }]
    },
    {
      "code" : "_IntraabdominalRoute",
      "target" : [{
        "code" : "_IntraabdominalRoute",
        "relationship" : "equivalent"
      }]
    },
    {
      "code" : "OJJ",
      "target" : [{
        "code" : "OJJ",
        "relationship" : "equivalent"
      }]
    },
    {
      "code" : "IDOUDMAB",
      "target" : [{
        "code" : "IDOUDMAB",
        "relationship" : "equivalent"
      }]
    },
    {
      "code" : "_IntraventricularRoute",
      "target" : [{
        "code" : "_IntraventricularRoute",
        "relationship" : "equivalent"
      }]
    },
    {
      "code" : "SLESINJ",
      "target" : [{
        "code" : "SLESINJ",
        "relationship" : "equivalent"
      }]
    },
    {
      "code" : "SWISHSPIT",
      "target" : [{
        "code" : "SWISHSPIT",
        "relationship" : "equivalent"
      }]
    },
    {
      "code" : "_Inhalation",
      "target" : [{
        "code" : "_Inhalation",
        "relationship" : "equivalent"
      }]
    },
    {
      "code" : "_IntraesophagealRoute",
      "target" : [{
        "code" : "_IntraesophagealRoute",
        "relationship" : "equivalent"
      }]
    },
    {
      "code" : "_Injection",
      "target" : [{
        "code" : "_Injection",
        "relationship" : "equivalent"
      }]
    },
    {
      "code" : "OT",
      "target" : [{
        "code" : "OT",
        "relationship" : "equivalent"
      }]
    },
    {
      "code" : "ICORNTA",
      "target" : [{
        "code" : "ICORNTA",
        "relationship" : "equivalent"
      }]
    },
    {
      "code" : "TRACH",
      "target" : [{
        "code" : "TRACH",
        "relationship" : "equivalent"
      }]
    },
    {
      "code" : "_VaginalRoute",
      "target" : [{
        "code" : "_VaginalRoute",
        "relationship" : "equivalent"
      }]
    },
    {
      "code" : "DRESS",
      "target" : [{
        "code" : "DRESS",
        "relationship" : "equivalent"
      }]
    },
    {
      "code" : "ISYNINJ",
      "target" : [{
        "code" : "ISYNINJ",
        "relationship" : "equivalent"
      }]
    },
    {
      "code" : "_LacrimalPunctaRoute",
      "target" : [{
        "code" : "_LacrimalPunctaRoute",
        "relationship" : "equivalent"
      }]
    },
    {
      "code" : "IVSPUSH",
      "target" : [{
        "code" : "IVSPUSH",
        "relationship" : "equivalent"
      }]
    },
    {
      "code" : "PO",
      "target" : [{
        "code" : "PO",
        "relationship" : "equivalent"
      }]
    },
    {
      "code" : "IOINSTL",
      "target" : [{
        "code" : "IOINSTL",
        "relationship" : "equivalent"
      }]
    },
    {
      "code" : "RECIRR",
      "target" : [{
        "code" : "RECIRR",
        "relationship" : "equivalent"
      }]
    },
    {
      "code" : "PR",
      "target" : [{
        "code" : "PR",
        "relationship" : "equivalent"
      }]
    },
    {
      "code" : "IESOPHINSTIL",
      "target" : [{
        "code" : "IESOPHINSTIL",
        "relationship" : "equivalent"
      }]
    },
    {
      "code" : "_BodySurfaceRoute",
      "target" : [{
        "code" : "_BodySurfaceRoute",
        "relationship" : "equivalent"
      }]
    },
    {
      "code" : "BLADINJ",
      "target" : [{
        "code" : "BLADINJ",
        "relationship" : "equivalent"
      }]
    },
    {
      "code" : "ITUBINJ",
      "target" : [{
        "code" : "ITUBINJ",
        "relationship" : "equivalent"
      }]
    },
    {
      "code" : "IAINJP",
      "target" : [{
        "code" : "IAINJP",
        "relationship" : "equivalent"
      }]
    },
    {
      "code" : "_OropharyngealRoute",
      "target" : [{
        "code" : "_OropharyngealRoute",
        "relationship" : "equivalent"
      }]
    },
    {
      "code" : "_UreteralRoute",
      "target" : [{
        "code" : "_UreteralRoute",
        "relationship" : "equivalent"
      }]
    },
    {
      "code" : "ORRINSE",
      "target" : [{
        "code" : "ORRINSE",
        "relationship" : "equivalent"
      }]
    },
    {
      "code" : "IDUCTINJ",
      "target" : [{
        "code" : "IDUCTINJ",
        "relationship" : "equivalent"
      }]
    },
    {
      "code" : "URETHINSTL",
      "target" : [{
        "code" : "URETHINSTL",
        "relationship" : "equivalent"
      }]
    },
    {
      "code" : "IPCARDINJ",
      "target" : [{
        "code" : "IPCARDINJ",
        "relationship" : "equivalent"
      }]
    },
    {
      "code" : "DENRINSE",
      "target" : [{
        "code" : "DENRINSE",
        "relationship" : "equivalent"
      }]
    },
    {
      "code" : "IOSURGINS",
      "target" : [{
        "code" : "IOSURGINS",
        "relationship" : "equivalent"
      }]
    },
    {
      "code" : "ITUMINJ",
      "target" : [{
        "code" : "ITUMINJ",
        "relationship" : "equivalent"
      }]
    },
    {
      "code" : "NAIL",
      "target" : [{
        "code" : "NAIL",
        "relationship" : "equivalent"
      }]
    },
    {
      "code" : "_IntralymphaticRoute",
      "target" : [{
        "code" : "_IntralymphaticRoute",
        "relationship" : "equivalent"
      }]
    },
    {
      "code" : "CERV",
      "target" : [{
        "code" : "CERV",
        "relationship" : "equivalent"
      }]
    },
    {
      "code" : "_TranstympanicRoute",
      "target" : [{
        "code" : "_TranstympanicRoute",
        "relationship" : "equivalent"
      }]
    },
    {
      "code" : "_CervicalRoute",
      "target" : [{
        "code" : "_CervicalRoute",
        "relationship" : "equivalent"
      }]
    },
    {
      "code" : "_IntraepithelialRoute",
      "target" : [{
        "code" : "_IntraepithelialRoute",
        "relationship" : "equivalent"
      }]
    },
    {
      "code" : "RECTINSTL",
      "target" : [{
        "code" : "RECTINSTL",
        "relationship" : "equivalent"
      }]
    },
    {
      "code" : "ILUMTA",
      "target" : [{
        "code" : "ILUMTA",
        "relationship" : "equivalent"
      }]
    },
    {
      "code" : "TRPLACINJ",
      "target" : [{
        "code" : "TRPLACINJ",
        "relationship" : "equivalent"
      }]
    },
    {
      "code" : "PDURINJ",
      "target" : [{
        "code" : "PDURINJ",
        "relationship" : "equivalent"
      }]
    },
    {
      "code" : "_SkinRoute",
      "target" : [{
        "code" : "_SkinRoute",
        "relationship" : "equivalent"
      }]
    },
    {
      "code" : "TRNSLING",
      "target" : [{
        "code" : "TRNSLING",
        "relationship" : "equivalent"
      }]
    },
    {
      "code" : "BUC",
      "target" : [{
        "code" : "BUC",
        "relationship" : "equivalent"
      }]
    },
    {
      "code" : "_IntraosseousRoute",
      "target" : [{
        "code" : "_IntraosseousRoute",
        "relationship" : "equivalent"
      }]
    },
    {
      "code" : "_UrethralRoute",
      "target" : [{
        "code" : "_UrethralRoute",
        "relationship" : "equivalent"
      }]
    },
    {
      "code" : "EXTCORPINJ",
      "target" : [{
        "code" : "EXTCORPINJ",
        "relationship" : "equivalent"
      }]
    },
    {
      "code" : "SL",
      "target" : [{
        "code" : "SL",
        "relationship" : "equivalent"
      }]
    },
    {
      "code" : "_Rinse",
      "target" : [{
        "code" : "_Rinse",
        "relationship" : "equivalent"
      }]
    },
    {
      "code" : "TRNSDERMD",
      "target" : [{
        "code" : "TRNSDERMD",
        "relationship" : "equivalent"
      }]
    },
    {
      "code" : "ILESINJ",
      "target" : [{
        "code" : "ILESINJ",
        "relationship" : "equivalent"
      }]
    },
    {
      "code" : "SQ",
      "target" : [{
        "code" : "SQ",
        "relationship" : "equivalent"
      }]
    },
    {
      "code" : "ITRACHINSTIL",
      "target" : [{
        "code" : "ITRACHINSTIL",
        "relationship" : "equivalent"
      }]
    },
    {
      "code" : "IOTOP",
      "target" : [{
        "code" : "IOTOP",
        "relationship" : "equivalent"
      }]
    },
    {
      "code" : "SUCK",
      "target" : [{
        "code" : "SUCK",
        "relationship" : "equivalent"
      }]
    },
    {
      "code" : "_SubmucosalRoute",
      "target" : [{
        "code" : "_SubmucosalRoute",
        "relationship" : "equivalent"
      }]
    },
    {
      "code" : "IVCC",
      "target" : [{
        "code" : "IVCC",
        "relationship" : "equivalent"
      }]
    },
    {
      "code" : "ISINJ",
      "target" : [{
        "code" : "ISINJ",
        "relationship" : "equivalent"
      }]
    },
    {
      "code" : "IVCI",
      "target" : [{
        "code" : "IVCI",
        "relationship" : "equivalent"
      }]
    },
    {
      "code" : "IAINJSP",
      "target" : [{
        "code" : "IAINJSP",
        "relationship" : "equivalent"
      }]
    },
    {
      "code" : "PDONTTA",
      "target" : [{
        "code" : "PDONTTA",
        "relationship" : "equivalent"
      }]
    },
    {
      "code" : "IABDINJ",
      "target" : [{
        "code" : "IABDINJ",
        "relationship" : "equivalent"
      }]
    },
    {
      "code" : "ICEREBINJ",
      "target" : [{
        "code" : "ICEREBINJ",
        "relationship" : "equivalent"
      }]
    },
    {
      "code" : "TRTRACHINJ",
      "target" : [{
        "code" : "TRTRACHINJ",
        "relationship" : "equivalent"
      }]
    },
    {
      "code" : "PERIANAL",
      "target" : [{
        "code" : "PERIANAL",
        "relationship" : "equivalent"
      }]
    },
    {
      "code" : "PDONTINJ",
      "target" : [{
        "code" : "PDONTINJ",
        "relationship" : "equivalent"
      }]
    },
    {
      "code" : "URETHINJ",
      "target" : [{
        "code" : "URETHINJ",
        "relationship" : "equivalent"
      }]
    },
    {
      "code" : "_IntrapulmonaryRoute",
      "target" : [{
        "code" : "_IntrapulmonaryRoute",
        "relationship" : "equivalent"
      }]
    },
    {
      "code" : "URETHINS",
      "target" : [{
        "code" : "URETHINS",
        "relationship" : "equivalent"
      }]
    },
    {
      "code" : "ITINJ",
      "target" : [{
        "code" : "ITINJ",
        "relationship" : "equivalent"
      }]
    },
    {
      "code" : "_IntradiscalRoute",
      "target" : [{
        "code" : "_IntradiscalRoute",
        "relationship" : "equivalent"
      }]
    },
    {
      "code" : "INTERSTITINJ",
      "target" : [{
        "code" : "INTERSTITINJ",
        "relationship" : "equivalent"
      }]
    },
    {
      "code" : "_IntrapleuralRoute",
      "target" : [{
        "code" : "_IntrapleuralRoute",
        "relationship" : "equivalent"
      }]
    },
    {
      "code" : "HEMODIFF",
      "target" : [{
        "code" : "HEMODIFF",
        "relationship" : "equivalent"
      }]
    },
    {
      "code" : "ORMUC",
      "target" : [{
        "code" : "ORMUC",
        "relationship" : "equivalent"
      }]
    },
    {
      "code" : "GARGLE",
      "target" : [{
        "code" : "GARGLE",
        "relationship" : "equivalent"
      }]
    },
    {
      "code" : "IVINJBOL",
      "target" : [{
        "code" : "IVINJBOL",
        "relationship" : "equivalent"
      }]
    },
    {
      "code" : "EXTRAMNINJ",
      "target" : [{
        "code" : "EXTRAMNINJ",
        "relationship" : "equivalent"
      }]
    },
    {
      "code" : "_IntrasinalRoute",
      "target" : [{
        "code" : "_IntrasinalRoute",
        "relationship" : "equivalent"
      }]
    },
    {
      "code" : "ITHORINJ",
      "target" : [{
        "code" : "ITHORINJ",
        "relationship" : "equivalent"
      }]
    },
    {
      "code" : "_IntradermalRoute",
      "target" : [{
        "code" : "_IntradermalRoute",
        "relationship" : "equivalent"
      }]
    },
    {
      "code" : "_IntratumorRoute",
      "target" : [{
        "code" : "_IntratumorRoute",
        "relationship" : "equivalent"
      }]
    },
    {
      "code" : "_IntraspinalRoute",
      "target" : [{
        "code" : "_IntraspinalRoute",
        "relationship" : "equivalent"
      }]
    },
    {
      "code" : "ILUMINJ",
      "target" : [{
        "code" : "ILUMINJ",
        "relationship" : "equivalent"
      }]
    },
    {
      "code" : "LARYNGINSTIL",
      "target" : [{
        "code" : "LARYNGINSTIL",
        "relationship" : "equivalent"
      }]
    },
    {
      "code" : "_SublesionalRoute",
      "target" : [{
        "code" : "_SublesionalRoute",
        "relationship" : "equivalent"
      }]
    },
    {
      "code" : "_IntratendinousRoute",
      "target" : [{
        "code" : "_IntratendinousRoute",
        "relationship" : "equivalent"
      }]
    },
    {
      "code" : "IOSSINJ",
      "target" : [{
        "code" : "IOSSINJ",
        "relationship" : "equivalent"
      }]
    },
    {
      "code" : "ILESIRR",
      "target" : [{
        "code" : "ILESIRR",
        "relationship" : "equivalent"
      }]
    },
    {
      "code" : "IOSSC",
      "target" : [{
        "code" : "IOSSC",
        "relationship" : "equivalent"
      }]
    },
    {
      "code" : "_Infusion",
      "target" : [{
        "code" : "_Infusion",
        "relationship" : "equivalent"
      }]
    },
    {
      "code" : "RECTAL",
      "target" : [{
        "code" : "RECTAL",
        "relationship" : "equivalent"
      }]
    },
    {
      "code" : "_Insertion",
      "target" : [{
        "code" : "_Insertion",
        "relationship" : "equivalent"
      }]
    },
    {
      "code" : "NASALINSTIL",
      "target" : [{
        "code" : "NASALINSTIL",
        "relationship" : "equivalent"
      }]
    },
    {
      "code" : "_IntracavitaryRoute",
      "target" : [{
        "code" : "_IntracavitaryRoute",
        "relationship" : "equivalent"
      }]
    },
    {
      "code" : "IGASTINSTIL",
      "target" : [{
        "code" : "IGASTINSTIL",
        "relationship" : "equivalent"
      }]
    },
    {
      "code" : "_NasalRoute",
      "target" : [{
        "code" : "_NasalRoute",
        "relationship" : "equivalent"
      }]
    },
    {
      "code" : "INSUF",
      "target" : [{
        "code" : "INSUF",
        "relationship" : "equivalent"
      }]
    },
    {
      "code" : "ETINSTL",
      "target" : [{
        "code" : "ETINSTL",
        "relationship" : "equivalent"
      }]
    },
    {
      "code" : "RECINSTL",
      "target" : [{
        "code" : "RECINSTL",
        "relationship" : "equivalent"
      }]
    },
    {
      "code" : "ITENDINJ",
      "target" : [{
        "code" : "ITENDINJ",
        "relationship" : "equivalent"
      }]
    },
    {
      "code" : "_IntratubularRoute",
      "target" : [{
        "code" : "_IntratubularRoute",
        "relationship" : "equivalent"
      }]
    },
    {
      "code" : "_IntrapericardialRoute",
      "target" : [{
        "code" : "_IntrapericardialRoute",
        "relationship" : "equivalent"
      }]
    },
    {
      "code" : "_PeriarticularRoute",
      "target" : [{
        "code" : "_PeriarticularRoute",
        "relationship" : "equivalent"
      }]
    },
    {
      "code" : "IVESINJ",
      "target" : [{
        "code" : "IVESINJ",
        "relationship" : "equivalent"
      }]
    },
    {
      "code" : "SMUCMAB",
      "target" : [{
        "code" : "SMUCMAB",
        "relationship" : "equivalent"
      }]
    },
    {
      "code" : "GINGINJ",
      "target" : [{
        "code" : "GINGINJ",
        "relationship" : "equivalent"
      }]
    },
    {
      "code" : "SWISHSWAL",
      "target" : [{
        "code" : "SWISHSWAL",
        "relationship" : "equivalent"
      }]
    },
    {
      "code" : "_SubconjunctivalRoute",
      "target" : [{
        "code" : "_SubconjunctivalRoute",
        "relationship" : "equivalent"
      }]
    },
    {
      "code" : "_Diffusion",
      "target" : [{
        "code" : "_Diffusion",
        "relationship" : "equivalent"
      }]
    },
    {
      "code" : "_GenitourinaryRoute",
      "target" : [{
        "code" : "_GenitourinaryRoute",
        "relationship" : "equivalent"
      }]
    },
    {
      "code" : "_IntralesionalRoute",
      "target" : [{
        "code" : "_IntralesionalRoute",
        "relationship" : "equivalent"
      }]
    },
    {
      "code" : "_UrinaryBladderRoute",
      "target" : [{
        "code" : "_UrinaryBladderRoute",
        "relationship" : "equivalent"
      }]
    },
    {
      "code" : "SOFTISINSTIL",
      "target" : [{
        "code" : "SOFTISINSTIL",
        "relationship" : "equivalent"
      }]
    },
    {
      "code" : "_IntracisternalRoute",
      "target" : [{
        "code" : "_IntracisternalRoute",
        "relationship" : "equivalent"
      }]
    },
    {
      "code" : "ICARTINJ",
      "target" : [{
        "code" : "ICARTINJ",
        "relationship" : "equivalent"
      }]
    },
    {
      "code" : "IUINJ",
      "target" : [{
        "code" : "IUINJ",
        "relationship" : "equivalent"
      }]
    },
    {
      "code" : "RBINJ",
      "target" : [{
        "code" : "RBINJ",
        "relationship" : "equivalent"
      }]
    },
    {
      "code" : "CTINSTL",
      "target" : [{
        "code" : "CTINSTL",
        "relationship" : "equivalent"
      }]
    },
    {
      "code" : "_IntraarticularRoute",
      "target" : [{
        "code" : "_IntraarticularRoute",
        "relationship" : "equivalent"
      }]
    },
    {
      "code" : "_IntracartilaginousRoute",
      "target" : [{
        "code" : "_IntracartilaginousRoute",
        "relationship" : "equivalent"
      }]
    },
    {
      "code" : "CECINSTL",
      "target" : [{
        "code" : "CECINSTL",
        "relationship" : "equivalent"
      }]
    },
    {
      "code" : "_AmnioticFluidSacRoute",
      "target" : [{
        "code" : "_AmnioticFluidSacRoute",
        "relationship" : "equivalent"
      }]
    },
    {
      "code" : "_RouteByMethod",
      "target" : [{
        "code" : "_RouteByMethod",
        "relationship" : "equivalent"
      }]
    },
    {
      "code" : "_ExtraAmnioticRoute",
      "target" : [{
        "code" : "_ExtraAmnioticRoute",
        "relationship" : "equivalent"
      }]
    },
    {
      "code" : "ORALTA",
      "target" : [{
        "code" : "ORALTA",
        "relationship" : "equivalent"
      }]
    },
    {
      "code" : "_IntracoronalRoute",
      "target" : [{
        "code" : "_IntracoronalRoute",
        "relationship" : "equivalent"
      }]
    },
    {
      "code" : "_TopicalAbsorptionRoute",
      "target" : [{
        "code" : "_TopicalAbsorptionRoute",
        "relationship" : "equivalent"
      }]
    },
    {
      "code" : "_IntraocularRoute",
      "target" : [{
        "code" : "_IntraocularRoute",
        "relationship" : "equivalent"
      }]
    },
    {
      "code" : "NTT",
      "target" : [{
        "code" : "NTT",
        "relationship" : "equivalent"
      }]
    },
    {
      "code" : "_IntravenousRoute",
      "target" : [{
        "code" : "_IntravenousRoute",
        "relationship" : "equivalent"
      }]
    },
    {
      "code" : "SOFTISINJ",
      "target" : [{
        "code" : "SOFTISINJ",
        "relationship" : "equivalent"
      }]
    },
    {
      "code" : "IVINJ",
      "target" : [{
        "code" : "IVINJ",
        "relationship" : "equivalent"
      }]
    },
    {
      "code" : "PDPINSTL",
      "target" : [{
        "code" : "PDPINSTL",
        "relationship" : "equivalent"
      }]
    },
    {
      "code" : "IVITIMPLNT",
      "target" : [{
        "code" : "IVITIMPLNT",
        "relationship" : "equivalent"
      }]
    },
    {
      "code" : "_TranstrachealRoute",
      "target" : [{
        "code" : "_TranstrachealRoute",
        "relationship" : "equivalent"
      }]
    },
    {
      "code" : "IPUMPINJ",
      "target" : [{
        "code" : "IPUMPINJ",
        "relationship" : "equivalent"
      }]
    },
    {
      "code" : "IVASCINJ",
      "target" : [{
        "code" : "IVASCINJ",
        "relationship" : "equivalent"
      }]
    },
    {
      "code" : "_IntraperitonealRoute",
      "target" : [{
        "code" : "_IntraperitonealRoute",
        "relationship" : "equivalent"
      }]
    },
    {
      "code" : "_IntraovarianRoute",
      "target" : [{
        "code" : "_IntraovarianRoute",
        "relationship" : "equivalent"
      }]
    },
    {
      "code" : "_PerinealRoute",
      "target" : [{
        "code" : "_PerinealRoute",
        "relationship" : "equivalent"
      }]
    },
    {
      "code" : "_LavageRoute",
      "target" : [{
        "code" : "_LavageRoute",
        "relationship" : "equivalent"
      }]
    },
    {
      "code" : "IEPIDINJ",
      "target" : [{
        "code" : "IEPIDINJ",
        "relationship" : "equivalent"
      }]
    },
    {
      "code" : "VAGINSI",
      "target" : [{
        "code" : "VAGINSI",
        "relationship" : "equivalent"
      }]
    },
    {
      "code" : "_Irrigation",
      "target" : [{
        "code" : "_Irrigation",
        "relationship" : "equivalent"
      }]
    },
    {
      "code" : "BLADIRR",
      "target" : [{
        "code" : "BLADIRR",
        "relationship" : "equivalent"
      }]
    },
    {
      "code" : "_OphthalmicRoute",
      "target" : [{
        "code" : "_OphthalmicRoute",
        "relationship" : "equivalent"
      }]
    },
    {
      "code" : "SQINFUS",
      "target" : [{
        "code" : "SQINFUS",
        "relationship" : "equivalent"
      }]
    },
    {
      "code" : "IILEALTA",
      "target" : [{
        "code" : "IILEALTA",
        "relationship" : "equivalent"
      }]
    },
    {
      "code" : "IPINHL",
      "target" : [{
        "code" : "IPINHL",
        "relationship" : "equivalent"
      }]
    },
    {
      "code" : "_PerineuralRoute",
      "target" : [{
        "code" : "_PerineuralRoute",
        "relationship" : "equivalent"
      }]
    },
    {
      "code" : "IAINJ",
      "target" : [{
        "code" : "IAINJ",
        "relationship" : "equivalent"
      }]
    },
    {
      "code" : "_IntracardiacRoute",
      "target" : [{
        "code" : "_IntracardiacRoute",
        "relationship" : "equivalent"
      }]
    },
    {
      "code" : "SUBCONJTA",
      "target" : [{
        "code" : "SUBCONJTA",
        "relationship" : "equivalent"
      }]
    },
    {
      "code" : "_BiliaryRoute",
      "target" : [{
        "code" : "_BiliaryRoute",
        "relationship" : "equivalent"
      }]
    },
    {
      "code" : "_IntravitrealRoute",
      "target" : [{
        "code" : "_IntravitrealRoute",
        "relationship" : "equivalent"
      }]
    },
    {
      "code" : "EPIDURINJ",
      "target" : [{
        "code" : "EPIDURINJ",
        "relationship" : "equivalent"
      }]
    },
    {
      "code" : "_EnteralRoute",
      "target" : [{
        "code" : "_EnteralRoute",
        "relationship" : "equivalent"
      }]
    },
    {
      "code" : "_Dissolve",
      "target" : [{
        "code" : "_Dissolve",
        "relationship" : "equivalent"
      }]
    },
    {
      "code" : "_Douche",
      "target" : [{
        "code" : "_Douche",
        "relationship" : "equivalent"
      }]
    },
    {
      "code" : "TOPICAL",
      "target" : [{
        "code" : "TOPICAL",
        "relationship" : "equivalent"
      }]
    },
    {
      "code" : "MUC",
      "target" : [{
        "code" : "MUC",
        "relationship" : "equivalent"
      }]
    },
    {
      "code" : "DOUCHE",
      "target" : [{
        "code" : "DOUCHE",
        "relationship" : "equivalent"
      }]
    },
    {
      "code" : "_PulmonaryRoute",
      "target" : [{
        "code" : "_PulmonaryRoute",
        "relationship" : "equivalent"
      }]
    },
    {
      "code" : "LPINS",
      "target" : [{
        "code" : "LPINS",
        "relationship" : "equivalent"
      }]
    },
    {
      "code" : "PNSINSTL",
      "target" : [{
        "code" : "PNSINSTL",
        "relationship" : "equivalent"
      }]
    },
    {
      "code" : "SOAK",
      "target" : [{
        "code" : "SOAK",
        "relationship" : "equivalent"
      }]
    },
    {
      "code" : "IMD",
      "target" : [{
        "code" : "IMD",
        "relationship" : "equivalent"
      }]
    },
    {
      "code" : "IVASCINFUS",
      "target" : [{
        "code" : "IVASCINFUS",
        "relationship" : "equivalent"
      }]
    },
    {
      "code" : "PARENTINJ",
      "target" : [{
        "code" : "PARENTINJ",
        "relationship" : "equivalent"
      }]
    },
    {
      "code" : "BLADIRRT",
      "target" : [{
        "code" : "BLADIRRT",
        "relationship" : "equivalent"
      }]
    },
    {
      "code" : "ITRACHMAB",
      "target" : [{
        "code" : "ITRACHMAB",
        "relationship" : "equivalent"
      }]
    },
    {
      "code" : "GIN",
      "target" : [{
        "code" : "GIN",
        "relationship" : "equivalent"
      }]
    },
    {
      "code" : "_IntraluminalRoute",
      "target" : [{
        "code" : "_IntraluminalRoute",
        "relationship" : "equivalent"
      }]
    },
    {
      "code" : "BLADIRRC",
      "target" : [{
        "code" : "BLADIRRC",
        "relationship" : "equivalent"
      }]
    },
    {
      "code" : "IMZ",
      "target" : [{
        "code" : "IMZ",
        "relationship" : "equivalent"
      }]
    },
    {
      "code" : "EXTCORPDIF",
      "target" : [{
        "code" : "EXTCORPDIF",
        "relationship" : "equivalent"
      }]
    },
    {
      "code" : "DISSOLVE",
      "target" : [{
        "code" : "DISSOLVE",
        "relationship" : "equivalent"
      }]
    },
    {
      "code" : "_IntrathoracicRoute",
      "target" : [{
        "code" : "_IntrathoracicRoute",
        "relationship" : "equivalent"
      }]
    },
    {
      "code" : "HAIR",
      "target" : [{
        "code" : "HAIR",
        "relationship" : "equivalent"
      }]
    },
    {
      "code" : "SCINJ",
      "target" : [{
        "code" : "SCINJ",
        "relationship" : "equivalent"
      }]
    },
    {
      "code" : "IUINSTL",
      "target" : [{
        "code" : "IUINSTL",
        "relationship" : "equivalent"
      }]
    },
    {
      "code" : "CHEW",
      "target" : [{
        "code" : "CHEW",
        "relationship" : "equivalent"
      }]
    },
    {
      "code" : "_Flush",
      "target" : [{
        "code" : "_Flush",
        "relationship" : "equivalent"
      }]
    },
    {
      "code" : "IMEDULINJ",
      "target" : [{
        "code" : "IMEDULINJ",
        "relationship" : "equivalent"
      }]
    },
    {
      "code" : "_Instillation",
      "target" : [{
        "code" : "_Instillation",
        "relationship" : "equivalent"
      }]
    },
    {
      "code" : "GJT",
      "target" : [{
        "code" : "GJT",
        "relationship" : "equivalent"
      }]
    },
    {
      "code" : "EFT",
      "target" : [{
        "code" : "EFT",
        "relationship" : "equivalent"
      }]
    },
    {
      "code" : "BLADINSTL",
      "target" : [{
        "code" : "BLADINSTL",
        "relationship" : "equivalent"
      }]
    },
    {
      "code" : "_ScalpRoute",
      "target" : [{
        "code" : "_ScalpRoute",
        "relationship" : "equivalent"
      }]
    },
    {
      "code" : "ORIFINHL",
      "target" : [{
        "code" : "ORIFINHL",
        "relationship" : "equivalent"
      }]
    },
    {
      "code" : "SUBARACHINJ",
      "target" : [{
        "code" : "SUBARACHINJ",
        "relationship" : "equivalent"
      }]
    },
    {
      "code" : "TRACHINSTL",
      "target" : [{
        "code" : "TRACHINSTL",
        "relationship" : "equivalent"
      }]
    },
    {
      "code" : "_NailRoute",
      "target" : [{
        "code" : "_NailRoute",
        "relationship" : "equivalent"
      }]
    },
    {
      "code" : "SUBMUCINJ",
      "target" : [{
        "code" : "SUBMUCINJ",
        "relationship" : "equivalent"
      }]
    },
    {
      "code" : "_TransmucosalRoute",
      "target" : [{
        "code" : "_TransmucosalRoute",
        "relationship" : "equivalent"
      }]
    },
    {
      "code" : "_TopicalApplication",
      "target" : [{
        "code" : "_TopicalApplication",
        "relationship" : "equivalent"
      }]
    },
    {
      "code" : "DEN",
      "target" : [{
        "code" : "DEN",
        "relationship" : "equivalent"
      }]
    },
    {
      "code" : "ICORPCAVINJ",
      "target" : [{
        "code" : "ICORPCAVINJ",
        "relationship" : "equivalent"
      }]
    },
    {
      "code" : "IGASTIRR",
      "target" : [{
        "code" : "IGASTIRR",
        "relationship" : "equivalent"
      }]
    },
    {
      "code" : "_TracheostomyRoute",
      "target" : [{
        "code" : "_TracheostomyRoute",
        "relationship" : "equivalent"
      }]
    },
    {
      "code" : "ISININSTIL",
      "target" : [{
        "code" : "ISININSTIL",
        "relationship" : "equivalent"
      }]
    },
    {
      "code" : "_IntratympanicRoute",
      "target" : [{
        "code" : "_IntratympanicRoute",
        "relationship" : "equivalent"
      }]
    },
    {
      "code" : "ICAUDINJ",
      "target" : [{
        "code" : "ICAUDINJ",
        "relationship" : "equivalent"
      }]
    }]
  }]
}